pulpcore/__init__.py
pulpcore/client/__init__.py
pulpcore/client/pulp_maven/__init__.py
pulpcore/client/pulp_maven/api_client.py
pulpcore/client/pulp_maven/api_response.py
pulpcore/client/pulp_maven/configuration.py
pulpcore/client/pulp_maven/exceptions.py
pulpcore/client/pulp_maven/py.typed
pulpcore/client/pulp_maven/rest.py
pulpcore/client/pulp_maven/api/__init__.py
pulpcore/client/pulp_maven/api/content_artifact_api.py
pulpcore/client/pulp_maven/api/distributions_maven_api.py
pulpcore/client/pulp_maven/api/pulp_maven_api.py
pulpcore/client/pulp_maven/api/remotes_maven_api.py
pulpcore/client/pulp_maven/api/repositories_maven_api.py
pulpcore/client/pulp_maven/api/repositories_maven_versions_api.py
pulpcore/client/pulp_maven/models/__init__.py
pulpcore/client/pulp_maven/models/async_operation_response.py
pulpcore/client/pulp_maven/models/content_summary_response.py
pulpcore/client/pulp_maven/models/maven_maven_artifact.py
pulpcore/client/pulp_maven/models/maven_maven_artifact_response.py
pulpcore/client/pulp_maven/models/maven_maven_distribution.py
pulpcore/client/pulp_maven/models/maven_maven_distribution_response.py
pulpcore/client/pulp_maven/models/maven_maven_remote.py
pulpcore/client/pulp_maven/models/maven_maven_remote_response.py
pulpcore/client/pulp_maven/models/maven_maven_remote_response_hidden_fields_inner.py
pulpcore/client/pulp_maven/models/maven_maven_repository.py
pulpcore/client/pulp_maven/models/maven_maven_repository_response.py
pulpcore/client/pulp_maven/models/paginated_repository_version_response_list.py
pulpcore/client/pulp_maven/models/paginatedmaven_maven_artifact_response_list.py
pulpcore/client/pulp_maven/models/paginatedmaven_maven_distribution_response_list.py
pulpcore/client/pulp_maven/models/paginatedmaven_maven_remote_response_list.py
pulpcore/client/pulp_maven/models/paginatedmaven_maven_repository_response_list.py
pulpcore/client/pulp_maven/models/patchedmaven_maven_distribution.py
pulp_maven_client-0.12.0.dist-info/METADATA
pulp_maven_client-0.12.0.dist-info/WHEEL
pulp_maven_client-0.12.0.dist-info/top_level.txt
pulp_maven_client-0.12.0.dist-info/RECORD
